resteasy.py
RESTEasy-3.1.2.dist-info/LICENSE
RESTEasy-3.1.2.dist-info/METADATA
RESTEasy-3.1.2.dist-info/WHEEL
RESTEasy-3.1.2.dist-info/top_level.txt
RESTEasy-3.1.2.dist-info/RECORD
