Metadata-Version: 2.1
Name: RESTEasy
Version: 3.1.2
Summary: REST API calls made easier
Home-page: https://github.com/rapidstack/RESTEasy
Download-URL: https://github.com/rapidstack/RESTEasy/archive/v3.1.2.tar.gz
Author: Arijit Basu
Author-email: sayanarijit@gmail.com
License: MIT
Keywords: REST API client
Classifier: Development Status :: 5 - Production/Stable
Classifier: Intended Audience :: Developers
Classifier: Intended Audience :: Information Technology
Classifier: License :: OSI Approved :: MIT License
Classifier: Natural Language :: English
Classifier: Programming Language :: Python
Classifier: Topic :: Internet
Classifier: Topic :: Utilities
Classifier: Topic :: Software Development
Classifier: Operating System :: MacOS
Classifier: Operating System :: Unix
Classifier: Operating System :: POSIX
Classifier: Operating System :: Microsoft
License-File: LICENSE
Requires-Dist: requests
Provides-Extra: dev
Requires-Dist: responses ; extra == 'dev'
Requires-Dist: pytest ; extra == 'dev'
Requires-Dist: pytest-cov ; extra == 'dev'
